{
  "time": [
    "2021/01/01/",
    "2021/02/01/",
    "2021/03/01/",
    "2021/04/01/",
    "2021/05/01/",
    "2021/06/01/",
    "2021/07/01/",
    "2021/08/01/",
    "2021/09/01/",
    "2021/10/01/",
    "2021/11/01/",
    "2021/12/01/"
  ],
  "nums": [
    {
      "name": "apnic",
      "data": [
        63883,
        66177,
        67250,
        69186,
        70345,
        72883,
        71122,
        77477,
        78484,
        44695,
        74140,
        83466
      ]
    },
    {
      "name": "afrinic",
      "data": [
        1667,
        1839,
        1977,
        1971,
        2067,
        2340,
        2494,
        2732,
        3175,
        3350,
        3758,
        4119
      ]
    },
    {
      "name": "lacnic",
      "data": [
        13219,
        13552,
        13926,
        14597,
        14809,
        15329,
        15897,
        16304,
        17149,
        16363,
        17843,
        19811
      ]
    },
    {
      "name": "ripencc",
      "data": [
        112570,
        115401,
        117843,
        121629,
        124876,
        127499,
        131283,
        133383,
        136491,
        138990,
        141557,
        144354
      ]
    },
    {
      "name": "arin",
      "data": [
        22674,
        23971,
        25909,
        29390,
        35636,
        42077,
        42296,
        45495,
        45600,
        42190,
        42699,
        44552
      ]
    }
  ]
}